Metadata-Version: 2.4
Name: pygremlinbox-gpl-3-0
Version: 1.4.0
Summary: Supply chain security testing package with GPL-3.0 licence
Author-email: PyGremlinBox Maintainer <simon@sigre.xyz>
License: GPL-3.0
Project-URL: Homepage, https://github.com/gocortexio/pygremlinbox
Project-URL: Repository, https://github.com/gocortexio/pygremlinbox
Keywords: security,testing,licence,supply-chain
Classifier: Development Status :: 4 - Beta
Classifier: Intended Audience :: Developers
Classifier: License :: OSI Approved :: GNU General Public License v3 (GPLv3)
Classifier: Operating System :: OS Independent
Classifier: Programming Language :: Python :: 3
Classifier: Programming Language :: Python :: 3.11
Classifier: Topic :: Security
Classifier: Topic :: Software Development :: Testing
Requires-Python: >=3.11
License-File: LICENCE
Dynamic: license-file
